sls_json_fast/__init__.py
sls_json_fast-0.1.2.dist-info/WHEEL
sls_json_fast-0.1.2.dist-info/METADATA
sls_json_fast-0.1.2.dist-info/RECORD
