Metadata-Version: 2.1
Name: sls-json-fast
Version: 0.1.2
Summary: aliyun sls log python for json
Author: JimZhang
Author-email: zzl22100048@gmail.com
Requires-Python: >=3.6,<4.0
Classifier: Programming Language :: Python :: 3
Classifier: Programming Language :: Python :: 3.6
Classifier: Programming Language :: Python :: 3.7
Classifier: Programming Language :: Python :: 3.8
Classifier: Programming Language :: Python :: 3.9
Requires-Dist: aliyun-log-python-sdk (>=0.7,<0.8)
Requires-Dist: protobuf (>=3.4.0,<4.0.0)
